pyellispeed-0.1.0.dist-info/METADATA
pyellispeed-0.1.0.dist-info/WHEEL
pyellispeed.libs/libgcc_s-5b5488a6.so.1
pyellispeed/__init__.py
pyellispeed/geometry.py
pyellispeed/analysis.py
pyellispeed/drawing.py
pyellispeed/pyellispeed.cpython-310-arm-linux-gnueabihf.so
pyellispeed-0.1.0.dist-info/RECORD
