Metadata-Version: 2.4
Name: pyellispeed
Version: 0.1.0
Classifier: License :: OSI Approved :: MIT License
Classifier: Programming Language :: Rust
Classifier: Programming Language :: Python :: 3
Classifier: Programming Language :: Python :: Implementation :: CPython
Classifier: Programming Language :: Python :: Implementation :: PyPy
Classifier: Development Status :: 3 - Alpha
Classifier: Intended Audience :: Developers
Classifier: Intended Audience :: Science/Research
Requires-Dist: numpy
Requires-Dist: pytest <=8.3.4 ; extra == 'test'
Requires-Dist: pytest-benchmark <=5.1.0 ; extra == 'test'
Provides-Extra: test
Summary: Ellipsoids drawing and analysis in 3D volumetric images.
Author-email: Guillaume Havard <guill.havard@gmail.com>
Requires-Python: >=3.8, <3.13
Project-URL: Homepage, https://github.com/guillaume-havard/speedestpy
Project-URL: Issues, https://github.com/guillaume-havard/speedestpy/issues
